pninexus/__init__.py
pninexus/filters/__init__.py
pninexus/filters/libh5LZF.so
pninexus/filters/libh5blosc.so
pninexus/filters/libh5bshuf.so
pninexus/filters/libh5bz2.so
pninexus/filters/libh5jpeg.so
pninexus/filters/libh5lz4.so
pninexus/filters/libh5mafisc.so
pninexus/filters/libh5zfp.so
pninexus/filters/liblzf_filter.so
pninexus/h5cpp/__init__.py
pninexus/h5cpp/_attribute.cpython-310-x86_64-linux-gnu.so
pninexus/h5cpp/_dataspace.cpython-310-x86_64-linux-gnu.so
pninexus/h5cpp/_datatype.cpython-310-x86_64-linux-gnu.so
pninexus/h5cpp/_file.cpython-310-x86_64-linux-gnu.so
pninexus/h5cpp/_filter.cpython-310-x86_64-linux-gnu.so
pninexus/h5cpp/_h5cpp.cpython-310-x86_64-linux-gnu.so
pninexus/h5cpp/_node.cpython-310-x86_64-linux-gnu.so
pninexus/h5cpp/_property.cpython-310-x86_64-linux-gnu.so
pninexus/h5cpp/attribute/__init__.py
pninexus/h5cpp/dataspace/__init__.py
pninexus/h5cpp/datatype/__init__.py
pninexus/h5cpp/file/__init__.py
pninexus/h5cpp/filter/__init__.py
pninexus/h5cpp/node/__init__.py
pninexus/h5cpp/property/__init__.py
pninexus/nexus/__init__.py
pninexus/nexus/_nexus.cpython-310-x86_64-linux-gnu.so
pninexus.libs/libaec-df4ff8a4.so.0.0.12
pninexus.libs/libblosc-1a5323ad.so.1.21.1
pninexus.libs/libboost_python310-80079748.so.1.74.0
pninexus.libs/libboost_regex-e2b8b679.so.1.74.0
pninexus.libs/libbrotlicommon-abf86ae9.so.1.0.9
pninexus.libs/libbrotlidec-db9dbda7.so.1.0.9
pninexus.libs/libbz2-5e516f77.so.1.0.4
pninexus.libs/libcom_err-f196091d.so.2.1
pninexus.libs/libcrypto-ee446395.so.3
pninexus.libs/libcurl-4a475a33.so.4.7.0
pninexus.libs/libffi-247da4d5.so.8.1.0
pninexus.libs/libgmp-4dc20a90.so.10.4.1
pninexus.libs/libgnutls-029add8e.so.30.31.0
pninexus.libs/libgssapi_krb5-ef9ec823.so.2.2
pninexus.libs/libh5cpp-cf5d864b.so.0.7.1
pninexus.libs/libhdf5_serial-12e4461a.so.103.3.0
pninexus.libs/libhdf5_serial_hl-701cc4c7.so.100.1.4
pninexus.libs/libhogweed-47d56894.so.6.4
pninexus.libs/libicudata-c1404396.so.70.1
pninexus-3.3.0.dist-info/LICENSE
pninexus-3.3.0.dist-info/METADATA
pninexus-3.3.0.dist-info/WHEEL
pninexus-3.3.0.dist-info/top_level.txt
pninexus-3.3.0.dist-info/RECORD
